adaptable_agents/__init__.py
adaptable_agents/anthropic_wrapper.py
adaptable_agents/client.py
adaptable_agents/openai_wrapper.py
adaptable_agents-0.1.3.dist-info/licenses/LICENSE
adaptable_agents-0.1.3.dist-info/METADATA
adaptable_agents-0.1.3.dist-info/WHEEL
adaptable_agents-0.1.3.dist-info/top_level.txt
adaptable_agents-0.1.3.dist-info/RECORD
