Metadata-Version: 2.4
Name: adaptable-agents
Version: 0.1.3
Summary: Python client for Adaptable Agents API - wrap your LLM clients with automatic context generation
Author: Adaptable Agents Team
License-Expression: MIT
Project-URL: Homepage, https://github.com/your-org/adaptable-agents
Project-URL: Documentation, https://docs.adaptable-agents.com
Project-URL: Repository, https://github.com/your-org/adaptable-agents-python-package
Classifier: Development Status :: 3 - Alpha
Classifier: Intended Audience :: Developers
Classifier: Topic :: Software Development :: Libraries :: Python Modules
Classifier: Programming Language :: Python :: 3
Classifier: Programming Language :: Python :: 3.8
Classifier: Programming Language :: Python :: 3.9
Classifier: Programming Language :: Python :: 3.10
Classifier: Programming Language :: Python :: 3.11
Classifier: Programming Language :: Python :: 3.12
Requires-Python: >=3.8
License-File: LICENSE
Requires-Dist: requests>=2.31.0
Requires-Dist: openai>=1.0.0
Requires-Dist: anthropic>=0.18.0
Provides-Extra: dev
Requires-Dist: pytest>=7.0.0; extra == "dev"
Requires-Dist: pytest-cov>=4.0.0; extra == "dev"
Requires-Dist: black>=23.0.0; extra == "dev"
Requires-Dist: mypy>=1.0.0; extra == "dev"
Dynamic: license-file
